Workbook

Sheet Exposure
A1: Supplier Exposure
A2: SKU-level data for the Aurelia–Orion negotiation
A3: SKU | B3: Component | C3: Origin | D3: Route | E3: Annual Units | F3: Unit Price | G3: Annual Spend | H3: Weeks Supply | I3: Criticality | J3: Qualified Alternate | K3: Supplier Increase | L3: Claimed Annual Impact
A4: AB-GLS-50 | B4: 50 ml decorated glass bottle | C4: Egypt | D4: Alexandria-Suez-Newark | E4: 1200000 | F4: 0.82 | G4: =E4*F4 -> 984000 | H4: 6 | I4: Launch critical | J4: Yes - 16 weeks | K4: 0.06 | L4: =G4*K4 -> 59040
A5: AB-GLS-30 | B5: 30 ml decorated glass bottle | C5: Egypt | D5: Alexandria-Suez-Newark | E5: 800000 | F5: 0.68 | G5: =E5*F5 -> 544000 | H5: 7 | I5: High | J5: Yes - 12 weeks | K5: 0.075 | L5: =G5*K5 -> 40800
A6: AB-ALC-01 | B6: Anodized aluminum collar | C6: Italy | D6: Genoa-Newark | E6: 2000000 | F6: 0.23 | G6: =E6*F6 -> 460000 | H6: 5 | I6: Launch critical | J6: No until Nov. | K6: 0.11 | L6: =G6*K6 -> 50600
A7: AB-ACT-02 | B7: Plastic actuator assembly | C7: China | D7: Shanghai-LA | E7: 1400000 | F7: 0.19 | G7: =E7*F7 -> 266000 | H7: 9 | I7: High | J7: Partial | K7: 0.25 | L7: =G7*K7 -> 66500
A8: AB-ACT-03 | B8: Premium actuator assembly | C8: China | D8: Shanghai-LA | E8: 600000 | F8: 0.31 | G8: =E8*F8 -> 186000 | H8: 8 | I8: High | J8: No | K8: 0.35 | L8: =G8*K8 -> 65100
A9: AB-PMP-01 | B9: Pump engine | C9: Germany | D9: Hamburg-Newark | E9: 2000000 | F9: 0.42 | G9: =E9*F9 -> 840000 | H9: 11 | I9: Medium | J9: Yes | K9: 0.04 | L9: =G9*K9 -> 33600
A10: AB-CAP-01 | B10: Overcap | C10: France | D10: Le Havre-Newark | E10: 1300000 | F10: 0.15 | G10: =E10*F10 -> 195000 | H10: 13 | I10: Low | J10: Yes | K10: 0 | L10: =G10*K10 -> 0
A11: AB-DSP-01 | B11: Airless dispenser | C11: Italy | D11: Genoa-Newark | E11: 400000 | F11: 0.74 | G11: =E11*F11 -> 296000 | H11: 6 | I11: Launch critical | J11: No | K11: 0.09 | L11: =G11*K11 -> 26640
A12: AB-JAR-50 | B12: 50 ml prestige jar | C12: Poland | D12: Gdansk-Newark | E12: 500000 | F12: 0.91 | G12: =E12*F12 -> 455000 | H12: 14 | I12: Medium | J12: Yes | K12: 0 | L12: =G12*K12 -> 0
A13: AB-LBL-01 | B13: Foil label | C13: United States | D13: Domestic truck | E13: 2100000 | F13: 0.04 | G13: =E13*F13 -> 84000 | H13: 10 | I13: Low | J13: Yes | K13: 0 | L13: =G13*K13 -> 0
F15: TOTAL | G15: =SUM(G4:G13) -> 4310000 | K15: Claimed impact | L15: =SUM(L4:L13) -> 342280

Sheet Claim_Audit
A1: Supplier Claim Audit
A2: Fictional calculations designed to reveal unsupported, duplicated, or expired claims
A3: SKU | B3: Supplier Basis | C3: Claim % | D3: Aurelia Supported % | E3: Claimed $ | F3: Supported $ | G3: Gap $ | H3: Contract Test | I3: Evidence Status | J3: Recommended Disposition | K3: Confidence | L3: Owner
A4: AB-GLS-50 | B4: Cape reroute + war risk | C4: 0.06 | D4: 0.032 | E4: =Exposure!L4 -> 59040 | F4: =Exposure!G4*D4 -> 31488 | G4: =E4-F4 -> 27552 | H4: 5.3 index/baseline; 7.3 mitigation | I4: Carrier quote; baseline available | J4: Counter with indexed 3.2%, quarterly reset | K4: High | L4: Category manager
A5: AB-GLS-30 | B5: Cape reroute + war risk | C5: 0.075 | D5: 0.028 | E5: =Exposure!L5 -> 40800 | F5: =Exposure!G5*D5 -> 15232 | G5: =E5-F5 -> 25568 | H5: 5.3 baseline; 4.5 no double recovery | I5: No baseline; insurance may duplicate quote | J5: Hold pending carrier and insurance proof | K5: Medium | L5: Logistics
A6: AB-ALC-01 | B6: Section 232 on full value | C6: 0.11 | D6: 0.037 | E6: =Exposure!L6 -> 50600 | F6: =Exposure!G6*D6 -> 17020 | G6: =E6-F6 -> 33580 | H6: 4.4 direct/actually paid; 12.4 audit | I6: Metal-content value not supplied | J6: Allow verified metal-content impact only | K6: Medium | L6: Trade compliance
A7: AB-ACT-02 | B7: Section 301 | C7: 0.25 | D7: 0.25 | E7: =Exposure!L7 -> 66500 | F7: =Exposure!G7*D7 -> 66500 | G7: =E7-F7 -> 0 | H7: 4.4 direct/actually paid | I7: Ten-digit HTS missing; plausible scope | J7: Conditional pending entry/HTS proof | K7: Medium | L7: Trade compliance
A8: AB-ACT-03 | B8: 25% Section 301 + expired 10% surcharge | C8: 0.35 | D8: 0.25 | E8: =Exposure!L8 -> 65100 | F8: =Exposure!G8*D8 -> 46500 | G8: =E8-F8 -> 18600 | H8: 4.4 effective duty; 4.5 no double recovery | I8: 10% Section 122 expired July 24 | J8: Reject expired 10%; verify remaining 25% | K8: High | L8: Trade compliance
A9: AB-PMP-01 | B9: Capacity reservation | C9: 0.04 | D9: 0 | E9: =Exposure!L9 -> 33600 | F9: 0 | G9: =E9-F9 -> 33600 | H9: 4.2 firm pricing; 12.4 audit | I9: No third-party invoice | J9: Reject without evidence and reciprocal commitment | K9: High | L9: Category manager
A10: AB-DSP-01 | B10: Portfolio tariff allocation | C10: 0.09 | D10: 0 | E10: =Exposure!L11 -> 26640 | F10: 0 | G10: =E10-F10 -> 26640 | H10: 4.4 directly attributable | I10: No itemized duty; Italy origin | J10: Reject portfolio allocation | K10: High | L10: Trade compliance
D12: TOTAL | E12: =SUM(E4:E10) -> 342280 | F12: =SUM(F4:F10) -> 176740 | G12: =SUM(G4:G10) -> 165540

Sheet Negotiation_Ladder
A1: Negotiation Control Tower
A2: Editable preparation sheet: objectives, give-get ladder, and authority guardrails
A3: Priority | B3: Aurelia Need | C3: Target | D3: Minimum / Walk-Away | E3: Supplier Likely Interest | F3: Potential Give | G3: Required Get | H3: Authority / Approval
A4: 1 | B4: Protect Q4 launch allocation | C4: 100% allocation + weekly recovery updates | D4: No less than 95% launch allocation | E4: Volume certainty | F4: 12-month volume signal | G4: Priority allocation + recovery plan | H4: GSM lead
A5: 2 | B5: Limit unsupported pass-through | C5: Verified SKU-level cost only | D5: No expired or undocumented charges | E5: Fast approval | F5: Accelerated review | G5: Customs/carrier evidence + audit | H5: Category manager
A6: 3 | B6: Create downward reset | C6: Quarterly two-way index reset | D6: Six-month sunset | E6: Margin protection | F6: Floor within agreed band | G6: Cap + two-way reset + sunset | H6: Finance if >3%
A7: 4 | B7: Improve continuity | C7: Qualified alternate by Nov. 30 | D7: Documented dual-source plan | E7: Longer-term award | F7: Conditional future-volume option | G7: Qualification milestones + owner | H7: Supply chain
A8: 5 | B8: Avoid precedent | C8: SKU-specific side letter | D8: No portfolio-wide adjustment | E8: Simple administration | F8: One consolidated review cadence | G8: No waiver / no precedent language | H8: Legal

Sheet Risk_Tripwires
A1: Risk Tripwires
A2: Measurable triggers that convert monitoring into action
A3: Risk | B3: Exposure | C3: Likelihood | D3: Impact | E3: Score | F3: Leading Indicator | G3: Trigger Threshold | H3: Action | I3: Owner | J3: Decision Date | K3: Status | L3: Evidence Source
A4: Egypt glass route delay | B4: Radiant Veil launch | C4: 4 | D4: 5 | E4: =C4*D4 -> 20 | F4: Confirmed vessel routing / ETA variance | G4: >7 days vs. baseline | H4: Reallocate glass and book alternate slot | I4: Supply chain | J4: 46262 | K4: Open | L4: Carrier schedule
A5: Aluminum collar shortfall | B5: No qualified alternate | C5: 3 | D5: 5 | E5: =C5*D5 -> 15 | F5: Weekly production attainment | G5: <95% for two weeks | H5: Executive allocation escalation | I5: Category manager | J5: 46260 | K5: Open | L5: Supplier recovery plan
A6: Unsupported tariff pass-through | B6: Margin and precedent | C6: 4 | D6: 4 | E6: =C6*D6 -> 16 | F6: Missing HTS/entry/value evidence | G6: Any line >$25K unverified | H6: Hold approval; customs review | I6: Trade compliance | J6: 46259 | K6: Open | L6: Claim audit
A7: Duplicate freight recovery | B7: Landed cost | C7: 3 | D7: 3 | E7: =C7*D7 -> 9 | F7: Insurance embedded in carrier quote | G7: Same cost in two charges | H7: Reject duplicate; require baseline | I7: Logistics | J7: 46258 | K7: Open | L7: Carrier/insurance invoices
A8: Launch allocation diversion | B8: Retailer set date | C8: 2 | D8: 5 | E8: =C8*D8 -> 10 | F8: Supplier allocation notice | G8: <95% confirmed allocation | H8: Invoke 7.1; leadership escalation | I8: GSM lead | J8: 46261 | K8: Open | L8: Allocation confirmation
A9: Alternate qualification slip | B9: Long-term resilience | C9: 3 | D9: 4 | E9: =C9*D9 -> 12 | F9: Tooling/sample milestones | G9: >10 business days late | H9: Fund expedite or second alternate | I9: Engineering | J9: 46280 | K9: Monitor | L9: Qualification tracker

Sheet Executive_Snapshot
A1: Executive Snapshot
A2: Decision-ready summary; formulas link to the claim audit
A4: Annual supplier spend | B4: =SUM(Exposure!G4:G13) -> 4310000
A5: Supplier claimed annual impact | B5: =SUM(Claim_Audit!E4:E10) -> 342280
A6: Aurelia supported annual impact | B6: =SUM(Claim_Audit!F4:F10) -> 176740
A7: Challengeable gap | B7: =SUM(Claim_Audit!G4:G10) -> 165540
A8: Launch-critical SKUs under 8 weeks | B8: =COUNTIFS(Exposure!H4:H13,"<8",Exposure!I4:I13,"Launch critical") -> 3
A9: Highest risk score | B9: =MAX(Risk_Tripwires!E4:E9) -> 20
A12: Recommended negotiation posture
A13: Accept verified, SKU-level incremental costs only. Trade a conditional volume signal for launch allocation, audit rights, a capped two-way quarterly reset, and supplier-funded alternate qualification milestones.

Sheet Data_Dictionary
A1: Data Dictionary
A2: Definitions, provenance, and explicit scenario assumptions
A3: Sheet | B3: Field / Range | C3: Definition | D3: Type | E3: Provenance / Guardrail
A4: Exposure | B4: Annual Units / Unit Price | C4: Fictional annualized demand and current contracted price | D4: Scenario assumption | E4: Do not represent as ELC or supplier actuals
A5: Exposure | B5: Claimed Annual Impact | C5: Annual spend multiplied by supplier requested increase | D5: Formula | E5: Directional annualization only
A6: Claim_Audit | B6: Aurelia Supported % | C6: Training estimate after applying evidence and contract tests | D6: Scenario assumption | E6: Requires customs, finance, logistics, and legal review
A7: Claim_Audit | B7: Confidence | C7: Confidence in recommended disposition based on supplied evidence | D7: Analyst judgment | E7: Not a probability
A8: Risk_Tripwires | B8: Likelihood / Impact | C8: 1-5 ordinal ratings | D8: Scenario assumption | E8: Scores prioritize discussion; they do not quantify loss
A9: External brief | B9: Tariff and shipping facts | C9: Authoritative public-source facts as of Aug. 17, 2026 | D9: Verified external fact | E9: Check for changes before real-world use
A10: All sheets | B10: Supplier and company names | C10: Aurelia Beauty Group and Orion Luxe Components | D10: Fictional | E10: Created solely for training
